README.rst
setup.py
libneko/__init__.py
libneko/aggregates.py
libneko/aiofiledb.py
libneko/aiojson.py
libneko/asyncinit.py
libneko/attr_generator.py
libneko/checks.py
libneko/clients.py
libneko/commands.py
libneko/converters.py
libneko/embeds.py
libneko/filesystem.py
libneko/funcmods.py
libneko/logging.py
libneko/other.py
libneko/permissions.py
libneko/properties.py
libneko/singleton.py
libneko/strings.py
libneko.egg-info/PKG-INFO
libneko.egg-info/SOURCES.txt
libneko.egg-info/dependency_links.txt
libneko.egg-info/requires.txt
libneko.egg-info/top_level.txt
libneko/extras/__init__.py
libneko/extras/help.py
libneko/extras/superuser.py
libneko/pag/__init__.py
libneko/pag/abc.py
libneko/pag/navigator.py
libneko/pag/optionpicker.py
libneko/pag/paginator.py
libneko/pag/reactionbuttons.py
libneko/pag/factory/__init__.py
libneko/pag/factory/basefactory.py
libneko/pag/factory/embedfactory.py
libneko/pag/factory/stringfactory.py
libneko/test/__init__.py
libneko/test/__main__.py
libneko/test/test_aggregates.py
libneko/test/test_aiofiledb.py
libneko/test/test_aiojson.py
libneko/test/test_asyncinit.py
libneko/test/test_commands.py
libneko/test/test_embeds.py
libneko/test/test_funcmods.py
libneko/test/test_properties.py
libneko/test/test_singleton.py
libneko/test/test_strings.py