Metadata-Version: 2.1
Name: libneko
Version: 0.24.7
Summary: 
